stopfortr
