Metadata-Version: 1.1
Name: stopfortr
Version: 0.7
Summary: Stopwords for Turkish Language
Home-page: https://github.com/taylangezici/stpfortr
Author: Taylan Gezici
Author-email: taylangezici@gmail.com
License: MIT
Download-URL: https://github.com/taylangezici/stopfortr/archive/refs/tags/v0.7.tar.gz
Keywords: none
Platform: UNKNOWN
Classifier: Development Status :: 3 - Alpha
Classifier: Intended Audience :: Developers
Classifier: Topic :: Software Development :: Build Tools
Classifier: License :: OSI Approved :: MIT License
Classifier: Programming Language :: Python :: 3
Classifier: Programming Language :: Python :: 3.4
Classifier: Programming Language :: Python :: 3.5
Classifier: Programming Language :: Python :: 3.6
